<?xml version="1.0" encoding="UTF-8"?>
<dcr:definitions xmlns:dcr="http://tk/schema/dcr" xmlns:dcrDi="http://tk/schema/dcrDi" xmlns:dc="http://www.omg.org/spec/DD/20100524/DC">
  <dcr:dcrGraph id="dcrGraph">
    <dcr:event id="Event_0wlsngk" description="A2" included="true" executed="false" pending="false" />
    <dcr:event id="Event_1detthw" description="A3" included="true" executed="false" pending="false" />
    <dcr:event id="Event_0m8xe2f" description="A1" included="true" executed="false" pending="true" />
    <dcr:event id="Event_1p48ml9" description="A4" included="true" executed="false" pending="true" />
    <dcr:event id="Event_0oe1qd7" description="A5" included="false" executed="false" pending="false" />
    <dcr:event id="Event_0d86f25" description="A6" included="true" executed="false" pending="false" />
    <dcr:event id="Event_03odm2z" description="A7" included="true" executed="false" pending="false" />
    <dcr:event id="Event_0dkyu6o" description="A8" included="true" executed="false" pending="false" />
    <dcr:event id="Event_01h0q3w" description="A9" included="true" executed="false" pending="false" />
    <dcr:event id="Event_17c01si" description="A10" included="true" executed="false" pending="false" />
    <dcr:event id="Event_1ryxjx2" description="A11" included="true" executed="false" pending="false" />
    <dcr:event id="Event_12ufbkd" description="A16" included="false" executed="false" pending="false" />
    <dcr:event id="Event_19mh6w1" description="A12" included="true" executed="false" pending="false" />
    <dcr:event id="Event_1sz267o" description="A13" included="true" executed="false" pending="false" />
    <dcr:event id="Event_0m1ydj3" description="A14" included="true" executed="false" pending="false" />
    <dcr:event id="Event_01nrrx2" description="A15" included="true" executed="false" pending="false" />
    <dcr:relation id="Relation_1rv19m3" type="condition" sourceRef="Event_0m8xe2f" targetRef="Event_0wlsngk" />
    <dcr:relation id="Relation_0xttdmm" type="condition" sourceRef="Event_1detthw" targetRef="Event_1p48ml9" />
    <dcr:relation id="Relation_1wikle5" type="condition" sourceRef="Event_0wlsngk" targetRef="Event_1detthw" />
    <dcr:relation id="Relation_1076idh" type="condition" sourceRef="Event_0d86f25" targetRef="Event_0dkyu6o" />
    <dcr:relation id="Relation_16eifmx" type="condition" sourceRef="Event_0dkyu6o" targetRef="Event_17c01si" />
    <dcr:relation id="Relation_0x6rbw2" type="condition" sourceRef="Event_17c01si" targetRef="Event_1ryxjx2" />
    <dcr:relation id="Relation_00c8jxv" type="condition" sourceRef="Event_03odm2z" targetRef="Event_0d86f25" />
    <dcr:relation id="Relation_1406j8c" type="condition" sourceRef="Event_0m8xe2f" targetRef="Event_19mh6w1" />
    <dcr:relation id="Relation_1671485" type="condition" sourceRef="Event_0m8xe2f" targetRef="Event_1sz267o" />
    <dcr:relation id="Relation_1gjcdcl" type="condition" sourceRef="Event_0m8xe2f" targetRef="Event_0m1ydj3" />
    <dcr:relation id="Relation_14tl158" type="condition" sourceRef="Event_0m8xe2f" targetRef="Event_01nrrx2" />
    <dcr:relation id="Relation_0hcfbxq" type="condition" sourceRef="Event_1detthw" targetRef="Event_0m1ydj3" />
    <dcr:relation id="Relation_1jiv1eg" type="condition" sourceRef="Event_1detthw" targetRef="Event_1sz267o" />
    <dcr:relation id="Relation_0hg66bz" type="condition" sourceRef="Event_1detthw" targetRef="Event_19mh6w1" />
    <dcr:relation id="Relation_1xesb0p" type="condition" sourceRef="Event_1detthw" targetRef="Event_01nrrx2" />
    <dcr:relation id="Relation_0voujtm" type="condition" sourceRef="Event_0m1ydj3" targetRef="Event_03odm2z" />
    <dcr:relation id="Relation_0mdcbq7" type="condition" sourceRef="Event_1sz267o" targetRef="Event_03odm2z" />
    <dcr:relation id="Relation_0klb529" type="condition" sourceRef="Event_19mh6w1" targetRef="Event_03odm2z" />
    <dcr:relation id="Relation_0ju1h1s" type="condition" sourceRef="Event_01nrrx2" targetRef="Event_03odm2z" />
    <dcr:relation id="Relation_1k9q850" type="response" sourceRef="Event_0m8xe2f" targetRef="Event_0wlsngk" />
    <dcr:relation id="Relation_0qg1z4w" type="response" sourceRef="Event_0m8xe2f" targetRef="Event_1detthw" />
    <dcr:relation id="Relation_1ezks5v" type="response" sourceRef="Event_0m1ydj3" targetRef="Event_03odm2z" />
    <dcr:relation id="Relation_0qpsbvj" type="response" sourceRef="Event_03odm2z" targetRef="Event_0oe1qd7" />
    <dcr:relation id="Relation_047lw0x" type="response" sourceRef="Event_0d86f25" targetRef="Event_0dkyu6o" />
    <dcr:relation id="Relation_1nw7xkm" type="response" sourceRef="Event_01h0q3w" targetRef="Event_0dkyu6o" />
    <dcr:relation id="Relation_105i4s0" type="response" sourceRef="Event_1ryxjx2" targetRef="Event_01h0q3w" />
    <dcr:relation id="Relation_03dwfd6" type="response" sourceRef="Event_0dkyu6o" targetRef="Event_17c01si" />
    <dcr:relation id="Relation_12o48bo" type="response" sourceRef="Event_17c01si" targetRef="Event_1ryxjx2" />
    <dcr:relation id="Relation_13f4e5e" type="response" sourceRef="Event_03odm2z" targetRef="Event_0d86f25" />
    <dcr:relation id="Relation_10iu9te" type="response" sourceRef="Event_03odm2z" targetRef="Event_12ufbkd" />
    <dcr:relation id="Relation_003ab9g" type="response" sourceRef="Event_1detthw" targetRef="Event_0m1ydj3" />
    <dcr:relation id="Relation_1cqhndw" type="response" sourceRef="Event_1detthw" targetRef="Event_1sz267o" />
    <dcr:relation id="Relation_1dg5w0p" type="response" sourceRef="Event_1detthw" targetRef="Event_19mh6w1" />
    <dcr:relation id="Relation_07t0kq5" type="response" sourceRef="Event_1detthw" targetRef="Event_01nrrx2" />
    <dcr:relation id="Relation_08nrkv2" type="response" sourceRef="Event_12ufbkd" targetRef="Event_01nrrx2" />
    <dcr:relation id="Relation_1aqbes3" type="response" sourceRef="Event_12ufbkd" targetRef="Event_0m1ydj3" />
    <dcr:relation id="Relation_166gp2n" type="response" sourceRef="Event_12ufbkd" targetRef="Event_1sz267o" />
    <dcr:relation id="Relation_0rio04j" type="response" sourceRef="Event_12ufbkd" targetRef="Event_19mh6w1" />
    <dcr:relation id="Relation_0e9qti6" type="exclude" sourceRef="Event_0m1ydj3" targetRef="Event_1p48ml9" />
    <dcr:relation id="Relation_14ajvg3" type="include" sourceRef="Event_03odm2z" targetRef="Event_0oe1qd7" />
    <dcr:relation id="Relation_07h9i95" type="include" sourceRef="Event_03odm2z" targetRef="Event_12ufbkd" />
    <dcr:relation id="Relation_0wjmtru" type="milestone" sourceRef="Event_19mh6w1" targetRef="Event_1sz267o" />
    <dcr:relation id="Relation_0a533b5" type="milestone" sourceRef="Event_1sz267o" targetRef="Event_0m1ydj3" />
    <dcr:relation id="Relation_1mtk4gb" type="milestone" sourceRef="Event_01nrrx2" targetRef="Event_1sz267o" />
  </dcr:dcrGraph>
  <dcrDi:dcrRootBoard id="dcrRootBoard">
    <dcrDi:dcrPlane id="dcrPlane" boardElement="dcrGraph">
      <dcrDi:relation id="Relation_1mtk4gb_di" boardElement="Relation_1mtk4gb">
        <dcrDi:waypoint x="745" y="1160" />
        <dcrDi:waypoint x="745" y="1070" />
      </dcrDi:relation>
      <dcrDi:relation id="Relation_0a533b5_di" boardElement="Relation_0a533b5">
        <dcrDi:waypoint x="810" y="995" />
        <dcrDi:waypoint x="890" y="995" />
      </dcrDi:relation>
      <dcrDi:relation id="Relation_0wjmtru_di" boardElement="Relation_0wjmtru">
        <dcrDi:waypoint x="600" y="995" />
        <dcrDi:waypoint x="680" y="995" />
      </dcrDi:relation>
      <dcrDi:relation id="Relation_07h9i95_di" boardElement="Relation_07h9i95">
        <dcrDi:waypoint x="1180" y="790" />
        <dcrDi:waypoint x="1180" y="1160" />
      </dcrDi:relation>
      <dcrDi:relation id="Relation_14ajvg3_di" boardElement="Relation_14ajvg3">
        <dcrDi:waypoint x="1150" y="640" />
        <dcrDi:waypoint x="1150" y="550" />
      </dcrDi:relation>
      <dcrDi:relation id="Relation_0e9qti6_di" boardElement="Relation_0e9qti6">
        <dcrDi:waypoint x="955" y="920" />
        <dcrDi:waypoint x="955" y="550" />
      </dcrDi:relation>
      <dcrDi:relation id="Relation_0rio04j_di" boardElement="Relation_0rio04j">
        <dcrDi:waypoint x="1100" y="1219" />
        <dcrDi:waypoint x="847" y="1159" />
        <dcrDi:waypoint x="680" y="1100" />
        <dcrDi:waypoint x="590" y="1070" />
      </dcrDi:relation>
      <dcrDi:relation id="Relation_166gp2n_di" boardElement="Relation_166gp2n">
        <dcrDi:waypoint x="1100" y="1220" />
        <dcrDi:waypoint x="850" y="1160" />
        <dcrDi:waypoint x="796" y="1070" />
      </dcrDi:relation>
      <dcrDi:relation id="Relation_1aqbes3_di" boardElement="Relation_1aqbes3">
        <dcrDi:waypoint x="1100" y="1220" />
        <dcrDi:waypoint x="1003" y="1070" />
      </dcrDi:relation>
      <dcrDi:relation id="Relation_08nrkv2_di" boardElement="Relation_08nrkv2">
        <dcrDi:waypoint x="1100" y="1220" />
        <dcrDi:waypoint x="810" y="1220" />
      </dcrDi:relation>
      <dcrDi:relation id="Relation_07t0kq5_di" boardElement="Relation_07t0kq5">
        <dcrDi:waypoint x="850" y="790" />
        <dcrDi:waypoint x="850" y="840" />
        <dcrDi:waypoint x="370" y="840" />
        <dcrDi:waypoint x="370" y="1260" />
        <dcrDi:waypoint x="680" y="1260" />
      </dcrDi:relation>
      <dcrDi:relation id="Relation_1dg5w0p_di" boardElement="Relation_1dg5w0p">
        <dcrDi:waypoint x="850" y="790" />
        <dcrDi:waypoint x="850" y="840" />
        <dcrDi:waypoint x="570" y="840" />
        <dcrDi:waypoint x="570" y="920" />
      </dcrDi:relation>
      <dcrDi:relation id="Relation_1cqhndw_di" boardElement="Relation_1cqhndw">
        <dcrDi:waypoint x="850" y="790" />
        <dcrDi:waypoint x="850" y="840" />
        <dcrDi:waypoint x="770" y="840" />
        <dcrDi:waypoint x="770" y="920" />
      </dcrDi:relation>
      <dcrDi:relation id="Relation_003ab9g_di" boardElement="Relation_003ab9g">
        <dcrDi:waypoint x="850" y="790" />
        <dcrDi:waypoint x="850" y="840" />
        <dcrDi:waypoint x="1000" y="840" />
        <dcrDi:waypoint x="1000" y="920" />
      </dcrDi:relation>
      <dcrDi:relation id="Relation_10iu9te_di" boardElement="Relation_10iu9te">
        <dcrDi:waypoint x="1150" y="790" />
        <dcrDi:waypoint x="1150" y="1160" />
      </dcrDi:relation>
      <dcrDi:relation id="Relation_13f4e5e_di" boardElement="Relation_13f4e5e">
        <dcrDi:waypoint x="1230" y="650" />
        <dcrDi:waypoint x="1255" y="650" />
        <dcrDi:waypoint x="1255" y="540" />
        <dcrDi:waypoint x="1280" y="540" />
      </dcrDi:relation>
      <dcrDi:relation id="Relation_12o48bo_di" boardElement="Relation_12o48bo">
        <dcrDi:waypoint x="1410" y="930" />
        <dcrDi:waypoint x="1490" y="930" />
      </dcrDi:relation>
      <dcrDi:relation id="Relation_03dwfd6_di" boardElement="Relation_03dwfd6">
        <dcrDi:waypoint x="1360" y="790" />
        <dcrDi:waypoint x="1360" y="870" />
      </dcrDi:relation>
      <dcrDi:relation id="Relation_105i4s0_di" boardElement="Relation_105i4s0">
        <dcrDi:waypoint x="1555" y="870" />
        <dcrDi:waypoint x="1555" y="790" />
      </dcrDi:relation>
      <dcrDi:relation id="Relation_1nw7xkm_di" boardElement="Relation_1nw7xkm">
        <dcrDi:waypoint x="1490" y="715" />
        <dcrDi:waypoint x="1410" y="715" />
      </dcrDi:relation>
      <dcrDi:relation id="Relation_047lw0x_di" boardElement="Relation_047lw0x">
        <dcrDi:waypoint x="1330" y="550" />
        <dcrDi:waypoint x="1330" y="640" />
      </dcrDi:relation>
      <dcrDi:relation id="Relation_0qpsbvj_di" boardElement="Relation_0qpsbvj">
        <dcrDi:waypoint x="1180" y="640" />
        <dcrDi:waypoint x="1180" y="550" />
      </dcrDi:relation>
      <dcrDi:relation id="Relation_1ezks5v_di" boardElement="Relation_1ezks5v">
        <dcrDi:waypoint x="980" y="920" />
        <dcrDi:waypoint x="980" y="715" />
        <dcrDi:waypoint x="1100" y="715" />
      </dcrDi:relation>
      <dcrDi:relation id="Relation_0qg1z4w_di" boardElement="Relation_0qg1z4w">
        <dcrDi:waypoint x="550" y="475" />
        <dcrDi:waypoint x="820" y="475" />
        <dcrDi:waypoint x="820" y="640" />
      </dcrDi:relation>
      <dcrDi:relation id="Relation_1k9q850_di" boardElement="Relation_1k9q850">
        <dcrDi:waypoint x="550" y="500" />
        <dcrDi:waypoint x="620" y="500" />
        <dcrDi:waypoint x="620" y="640" />
      </dcrDi:relation>
      <dcrDi:relation id="Relation_0ju1h1s_di" boardElement="Relation_0ju1h1s">
        <dcrDi:waypoint x="810" y="1220" />
        <dcrDi:waypoint x="1020" y="1170" />
        <dcrDi:waypoint x="1120" y="790" />
      </dcrDi:relation>
      <dcrDi:relation id="Relation_0klb529_di" boardElement="Relation_0klb529">
        <dcrDi:waypoint x="535" y="1070" />
        <dcrDi:waypoint x="535" y="1100" />
        <dcrDi:waypoint x="1130" y="1100" />
        <dcrDi:waypoint x="1130" y="790" />
      </dcrDi:relation>
      <dcrDi:relation id="Relation_0mdcbq7_di" boardElement="Relation_0mdcbq7">
        <dcrDi:waypoint x="770" y="1070" />
        <dcrDi:waypoint x="770" y="1100" />
        <dcrDi:waypoint x="1130" y="1100" />
        <dcrDi:waypoint x="1130" y="790" />
      </dcrDi:relation>
      <dcrDi:relation id="Relation_0voujtm_di" boardElement="Relation_0voujtm">
        <dcrDi:waypoint x="1020" y="995" />
        <dcrDi:waypoint x="1130" y="995" />
        <dcrDi:waypoint x="1130" y="790" />
      </dcrDi:relation>
      <dcrDi:relation id="Relation_1xesb0p_di" boardElement="Relation_1xesb0p">
        <dcrDi:waypoint x="820" y="790" />
        <dcrDi:waypoint x="820" y="870" />
        <dcrDi:waypoint x="390" y="870" />
        <dcrDi:waypoint x="390" y="1200" />
        <dcrDi:waypoint x="680" y="1200" />
      </dcrDi:relation>
      <dcrDi:relation id="Relation_0hg66bz_di" boardElement="Relation_0hg66bz">
        <dcrDi:waypoint x="820" y="790" />
        <dcrDi:waypoint x="820" y="870" />
        <dcrDi:waypoint x="535" y="870" />
        <dcrDi:waypoint x="535" y="920" />
      </dcrDi:relation>
      <dcrDi:relation id="Relation_1jiv1eg_di" boardElement="Relation_1jiv1eg">
        <dcrDi:waypoint x="820" y="790" />
        <dcrDi:waypoint x="820" y="870" />
        <dcrDi:waypoint x="710" y="870" />
        <dcrDi:waypoint x="710" y="920" />
      </dcrDi:relation>
      <dcrDi:relation id="Relation_0hcfbxq_di" boardElement="Relation_0hcfbxq">
        <dcrDi:waypoint x="820" y="790" />
        <dcrDi:waypoint x="820" y="870" />
        <dcrDi:waypoint x="910" y="870" />
        <dcrDi:waypoint x="910" y="920" />
      </dcrDi:relation>
      <dcrDi:relation id="Relation_14tl158_di" boardElement="Relation_14tl158">
        <dcrDi:waypoint x="485" y="550" />
        <dcrDi:waypoint x="485" y="850" />
        <dcrDi:waypoint x="410" y="850" />
        <dcrDi:waypoint x="410" y="1235" />
        <dcrDi:waypoint x="680" y="1235" />
      </dcrDi:relation>
      <dcrDi:relation id="Relation_1gjcdcl_di" boardElement="Relation_1gjcdcl">
        <dcrDi:waypoint x="485" y="550" />
        <dcrDi:waypoint x="485" y="850" />
        <dcrDi:waypoint x="930" y="850" />
        <dcrDi:waypoint x="930" y="920" />
      </dcrDi:relation>
      <dcrDi:relation id="Relation_1671485_di" boardElement="Relation_1671485">
        <dcrDi:waypoint x="485" y="550" />
        <dcrDi:waypoint x="485" y="850" />
        <dcrDi:waypoint x="745" y="850" />
        <dcrDi:waypoint x="745" y="920" />
      </dcrDi:relation>
      <dcrDi:relation id="Relation_1406j8c_di" boardElement="Relation_1406j8c">
        <dcrDi:waypoint x="485" y="550" />
        <dcrDi:waypoint x="485" y="850" />
        <dcrDi:waypoint x="410" y="850" />
        <dcrDi:waypoint x="410" y="995" />
        <dcrDi:waypoint x="470" y="995" />
      </dcrDi:relation>
      <dcrDi:relation id="Relation_00c8jxv_di" boardElement="Relation_00c8jxv">
        <dcrDi:waypoint x="1230" y="640" />
        <dcrDi:waypoint x="1240" y="640" />
        <dcrDi:waypoint x="1240" y="520" />
        <dcrDi:waypoint x="1280" y="520" />
      </dcrDi:relation>
      <dcrDi:relation id="Relation_0x6rbw2_di" boardElement="Relation_0x6rbw2">
        <dcrDi:waypoint x="1410" y="960" />
        <dcrDi:waypoint x="1490" y="960" />
      </dcrDi:relation>
      <dcrDi:relation id="Relation_16eifmx_di" boardElement="Relation_16eifmx">
        <dcrDi:waypoint x="1330" y="790" />
        <dcrDi:waypoint x="1330" y="870" />
      </dcrDi:relation>
      <dcrDi:relation id="Relation_1076idh_di" boardElement="Relation_1076idh">
        <dcrDi:waypoint x="1360" y="550" />
        <dcrDi:waypoint x="1360" y="640" />
      </dcrDi:relation>
      <dcrDi:relation id="Relation_1wikle5_di" boardElement="Relation_1wikle5">
        <dcrDi:waypoint x="700" y="715" />
        <dcrDi:waypoint x="770" y="715" />
      </dcrDi:relation>
      <dcrDi:relation id="Relation_0xttdmm_di" boardElement="Relation_0xttdmm">
        <dcrDi:waypoint x="850" y="640" />
        <dcrDi:waypoint x="850" y="475" />
        <dcrDi:waypoint x="920" y="475" />
      </dcrDi:relation>
      <dcrDi:relation id="Relation_1rv19m3_di" boardElement="Relation_1rv19m3">
        <dcrDi:waypoint x="550" y="520" />
        <dcrDi:waypoint x="600" y="520" />
        <dcrDi:waypoint x="600" y="640" />
      </dcrDi:relation>
      <dcrDi:dcrShape id="Event_0wlsngk_di" boardElement="Event_0wlsngk">
        <dc:Bounds x="570" y="640" width="130" height="150" />
      </dcrDi:dcrShape>
      <dcrDi:dcrShape id="Event_1detthw_di" boardElement="Event_1detthw">
        <dc:Bounds x="770" y="640" width="130" height="150" />
      </dcrDi:dcrShape>
      <dcrDi:dcrShape id="Event_0m8xe2f_di" boardElement="Event_0m8xe2f">
        <dc:Bounds x="420" y="400" width="130" height="150" />
      </dcrDi:dcrShape>
      <dcrDi:dcrShape id="Event_1p48ml9_di" boardElement="Event_1p48ml9">
        <dc:Bounds x="920" y="400" width="130" height="150" />
      </dcrDi:dcrShape>
      <dcrDi:dcrShape id="Event_0oe1qd7_di" boardElement="Event_0oe1qd7">
        <dc:Bounds x="1100" y="400" width="130" height="150" />
      </dcrDi:dcrShape>
      <dcrDi:dcrShape id="Event_0d86f25_di" boardElement="Event_0d86f25">
        <dc:Bounds x="1280" y="400" width="130" height="150" />
      </dcrDi:dcrShape>
      <dcrDi:dcrShape id="Event_03odm2z_di" boardElement="Event_03odm2z">
        <dc:Bounds x="1100" y="640" width="130" height="150" />
      </dcrDi:dcrShape>
      <dcrDi:dcrShape id="Event_0dkyu6o_di" boardElement="Event_0dkyu6o">
        <dc:Bounds x="1280" y="640" width="130" height="150" />
      </dcrDi:dcrShape>
      <dcrDi:dcrShape id="Event_01h0q3w_di" boardElement="Event_01h0q3w">
        <dc:Bounds x="1490" y="640" width="130" height="150" />
      </dcrDi:dcrShape>
      <dcrDi:dcrShape id="Event_17c01si_di" boardElement="Event_17c01si">
        <dc:Bounds x="1280" y="870" width="130" height="150" />
      </dcrDi:dcrShape>
      <dcrDi:dcrShape id="Event_1ryxjx2_di" boardElement="Event_1ryxjx2">
        <dc:Bounds x="1490" y="870" width="130" height="150" />
      </dcrDi:dcrShape>
      <dcrDi:dcrShape id="Event_12ufbkd_di" boardElement="Event_12ufbkd">
        <dc:Bounds x="1100" y="1160" width="130" height="150" />
      </dcrDi:dcrShape>
      <dcrDi:dcrShape id="Event_19mh6w1_di" boardElement="Event_19mh6w1">
        <dc:Bounds x="470" y="920" width="130" height="150" />
      </dcrDi:dcrShape>
      <dcrDi:dcrShape id="Event_1sz267o_di" boardElement="Event_1sz267o">
        <dc:Bounds x="680" y="920" width="130" height="150" />
      </dcrDi:dcrShape>
      <dcrDi:dcrShape id="Event_0m1ydj3_di" boardElement="Event_0m1ydj3">
        <dc:Bounds x="890" y="920" width="130" height="150" />
      </dcrDi:dcrShape>
      <dcrDi:dcrShape id="Event_01nrrx2_di" boardElement="Event_01nrrx2">
        <dc:Bounds x="680" y="1160" width="130" height="150" />
      </dcrDi:dcrShape>
    </dcrDi:dcrPlane>
  </dcrDi:dcrRootBoard>
</dcr:definitions>
